Email_Finder_Igor/__init__.py
Email_Finder_Igor/main.py
Email_Finder_Igor-0.0.1.dist-info/LICENSE
Email_Finder_Igor-0.0.1.dist-info/METADATA
Email_Finder_Igor-0.0.1.dist-info/WHEEL
Email_Finder_Igor-0.0.1.dist-info/top_level.txt
Email_Finder_Igor-0.0.1.dist-info/RECORD
